{
  "$schema": "https://ui.shadcn.com/schema/registry-item.json",
  "name": "cta-with-top-large-image",
  "title": "Cta With Top Large Image",
  "description": "Marketing cta variant for email templates",
  "dependencies": [
    "jsx-email"
  ],
  "registryDependencies": [
    "https://emailcn.vercel.app/r/jsx-email/default-fonts.json",
    "https://emailcn.vercel.app/r/jsx-email/theme-default.json"
  ],
  "files": [
    {
      "path": "registry/bases/jsx-email/ui/marketing/cta/cta-with-top-large-image.tsx",
      "content": "import {\n  Body,\n  Container,\n  Head,\n  Html,\n  Preview,\n  Section,\n  Row,\n  Column,\n  Heading,\n  Text,\n  Link,\n  Img,\n} from \"jsx-email\";\nimport { Fragment } from \"react\";\n\nimport { DefaultFonts } from \"@/components/email/default\";\nimport { defaultTheme } from \"@/components/email/theme-default\";\nimport type { EmailThemeTokens } from \"@/components/email/theme-default\";\n\nexport interface CTAWithTopLargeImageProps {\n  theme?: EmailThemeTokens;\n  heading?: string;\n  subtext?: string;\n  ctaLabel?: string;\n  ctaHref?: string;\n  imageSrc?: string;\n  imageAlt?: string;\n  pageBackgroundColor?: string;\n  backgroundColor?: string;\n  headingColor?: string;\n  textColor?: string;\n  buttonBackgroundColor?: string;\n  buttonTextColor?: string;\n}\n\nconst fontFamily =\n  'Inter, ui-sans-serif, system-ui, -apple-system, \"Segoe UI\", sans-serif';\n\nconst responsiveStyles = `\n  @media only screen and (max-width: 599px) {\n    .cta-top-image-content {\n      padding-left: 24px !important;\n      padding-right: 24px !important;\n    }\n  }\n\n  .cta-top-image-button:hover {\n    background-color: #4338ca !important;\n  }\n`;\n\ntype SectionProps = Omit<CTAWithTopLargeImageProps, \"theme\">;\n\nconst defaultSectionProps = {\n  backgroundColor: \"#fffffe\",\n  buttonBackgroundColor: \"#4f46e5\",\n  buttonTextColor: \"#f8fafc\",\n  ctaHref: \"https://example.com/\",\n  ctaLabel: \"Activate & Save\",\n  heading: \"Built for the journey ahead.\",\n  headingColor: \"#030712\",\n  imageAlt: \"\",\n  imageSrc:\n    \"https://emailcn.vercel.app/api/email-assets/cta/cta-with-image-1.jpg\",\n  pageBackgroundColor: \"#f1f5f9\",\n  subtext:\n    \"You’re one step away from exploring our latest outdoor essentials. Confirm your email to complete your setup and get 10% off your first order.\",\n  textColor: \"#4b5563\",\n} satisfies SectionProps;\n\nexport const CTAWithTopLargeImageSection = (props: SectionProps) => {\n  const resolved = { ...defaultSectionProps, ...props };\n\n  return (\n    <Section\n      style={{ backgroundColor: resolved.pageBackgroundColor }}\n      width=\"100%\"\n    >\n      <Fragment>\n        <Row>\n          <Column>&zwj;</Column>\n          <Column\n            style={{\n              backgroundColor: resolved.backgroundColor,\n              maxWidth: \"100%\",\n              paddingBottom: \"44px\",\n              width: \"600px\",\n            }}\n          >\n            <Section width=\"100%\">\n              <Fragment>\n                <Row>\n                  <Column\n                    className=\"cta-top-image-content\"\n                    style={{ padding: \"0 64px\", textAlign: \"center\" }}\n                  >\n                    <Section style={{ lineHeight: \"44px\" }}>&zwj;</Section>\n                    <Img\n                      alt={resolved.imageAlt}\n                      src={resolved.imageSrc}\n                      style={{\n                        borderRadius: \"4px\",\n                        maxWidth: \"100%\",\n                        verticalAlign: \"middle\",\n                      }}\n                      width=\"472\"\n                    />\n                    <Section style={{ lineHeight: \"24px\" }}>&zwj;</Section>\n                    <Heading\n                      style={{\n                        color: resolved.headingColor,\n                        fontFamily,\n                        fontSize: \"30px\",\n                        fontWeight: 500,\n                        lineHeight: \"36px\",\n                        margin: 0,\n                        textAlign: \"center\",\n                      }}\n                      as=\"h2\"\n                    >\n                      {resolved.heading}\n                    </Heading>\n                    <Section style={{ lineHeight: \"24px\" }}>&zwj;</Section>\n                    <Text\n                      style={{\n                        color: resolved.textColor,\n                        fontFamily,\n                        fontSize: \"16px\",\n                        fontWeight: 300,\n                        lineHeight: \"24px\",\n                        margin: 0,\n                        textAlign: \"center\",\n                      }}\n                    >\n                      {resolved.subtext}\n                    </Text>\n                    <Section style={{ lineHeight: \"36px\" }}>&zwj;</Section>\n                    <Link\n                      className=\"cta-top-image-button\"\n                      href={resolved.ctaHref}\n                      style={{\n                        backgroundColor: resolved.buttonBackgroundColor,\n                        borderRadius: \"8px\",\n                        color: resolved.buttonTextColor,\n                        display: \"inline-block\",\n                        fontFamily,\n                        fontSize: \"16px\",\n                        fontWeight: 500,\n                        lineHeight: \"24px\",\n                        padding: \"10px 22px\",\n                        textAlign: \"center\",\n                        textDecoration: \"none\",\n                      }}\n                    >\n                      {resolved.ctaLabel}\n                    </Link>\n                  </Column>\n                </Row>\n              </Fragment>\n            </Section>\n          </Column>\n          <Column>&zwj;</Column>\n        </Row>\n      </Fragment>\n    </Section>\n  );\n};\n\nexport const CTAWithTopLargeImage = ({\n  pageBackgroundColor = \"#f1f5f9\",\n  theme = defaultTheme,\n  ...props\n}: CTAWithTopLargeImageProps) => (\n  <Html>\n    <Head>\n      <DefaultFonts />\n      <style dangerouslySetInnerHTML={{ __html: responsiveStyles }} />\n    </Head>\n    <Preview>{props.heading ?? defaultSectionProps.heading}</Preview>\n    <Body\n      style={{\n        backgroundColor: pageBackgroundColor,\n        fontFamily: theme.fontFamily,\n        margin: 0,\n      }}\n    >\n      <Container\n        style={{ margin: \"0 auto\", maxWidth: \"600px\", width: \"600px\" }}\n      >\n        <CTAWithTopLargeImageSection\n          {...props}\n          pageBackgroundColor={pageBackgroundColor}\n        />\n      </Container>\n    </Body>\n  </Html>\n);\n\nCTAWithTopLargeImage.PreviewProps = {\n  theme: defaultTheme,\n} satisfies CTAWithTopLargeImageProps;\n",
      "type": "registry:component",
      "target": "components/email/cta-with-top-large-image.tsx"
    }
  ],
  "categories": [
    "email-component"
  ],
  "type": "registry:component"
}
