{
  "$schema": "https://ui.shadcn.com/schema/registry-item.json",
  "name": "footer-with-content-and-cta",
  "title": "Footer With Content And Cta",
  "description": "Marketing footers variant for email templates",
  "dependencies": [
    "jsx-email"
  ],
  "registryDependencies": [
    "https://emailcn.vercel.app/r/jsx-email/default-fonts.json",
    "https://emailcn.vercel.app/r/jsx-email/theme-default.json"
  ],
  "files": [
    {
      "path": "registry/bases/jsx-email/ui/marketing/footers/footer-with-content-and-cta.tsx",
      "content": "import {\n  Body,\n  Head,\n  Html,\n  Preview,\n  Section,\n  Row,\n  Column,\n  Text,\n  Link,\n  Img,\n} from \"jsx-email\";\nimport { Fragment } from \"react\";\n\nimport { DefaultFonts } from \"@/components/email/default\";\nimport { defaultTheme } from \"@/components/email/theme-default\";\nimport type { EmailThemeTokens } from \"@/components/email/theme-default\";\n\nexport type FooterWithContentAndCtaVariant =\n  | \"centered\"\n  | \"left-aligned\"\n  | \"right-aligned\";\n\nexport interface FooterWithContentAndCtaProps {\n  theme?: EmailThemeTokens;\n  heading?: string;\n  subtext?: string;\n  ctaLabel?: string;\n  ctaHref?: string;\n  logoSrc?: string;\n  logoAlt?: string;\n  updatePreferencesHref?: string;\n  unsubscribeHref?: string;\n  pageBackgroundColor?: string;\n  backgroundColor?: string;\n  headingColor?: string;\n  textColor?: string;\n  mutedTextColor?: string;\n  buttonColor?: string;\n  buttonTextColor?: string;\n  variant?: FooterWithContentAndCtaVariant;\n}\n\nconst fontFamily =\n  'Inter, ui-sans-serif, system-ui, -apple-system, \"Segoe UI\", sans-serif';\n\nconst defaults = {\n  backgroundColor: \"#fffffe\",\n  buttonColor: \"#4f46e5\",\n  buttonTextColor: \"#fffffe\",\n  ctaHref: \"https://example.com\",\n  ctaLabel: \"Visit website\",\n  heading: \"Start sending professionally\\ndesigned emails today\",\n  headingColor: \"#030712\",\n  logoAlt: \"Maizzle\",\n  logoSrc: \"https://emailcn.vercel.app/api/email-assets/maizzle-insignia.png\",\n  mutedTextColor: \"#d1d5db\",\n  pageBackgroundColor: \"#f1f5f9\",\n  subtext:\n    \"Lorem ipsum dolor sit amet consectetur. Eget aenean sed sit sed in sapien. Vel auctor arcu nulla consectetur sed.\",\n  textColor: \"#6b7280\",\n  unsubscribeHref: \"https://example.com/unsub\",\n  updatePreferencesHref: \"https://example.com/update\",\n};\n\ntype SectionProps = Omit<FooterWithContentAndCtaProps, \"theme\">;\ntype ResolvedProps = typeof defaults &\n  SectionProps & { variant: FooterWithContentAndCtaVariant };\n\nconst Multiline = ({ text }: { text: string }) =>\n  text.split(\"\\n\").map((line, index) => (\n    <Fragment key={line}>\n      {index > 0 ? <br /> : null}\n      {line}\n    </Fragment>\n  ));\n\nexport const FooterWithContentAndCtaSection = (props: SectionProps) => {\n  const resolved = {\n    ...defaults,\n    ...props,\n    variant: props.variant ?? \"centered\",\n  } as ResolvedProps;\n  const textAlign = {\n    centered: \"center\",\n    \"left-aligned\": \"left\",\n    \"right-aligned\": \"right\",\n  }[resolved.variant] as \"center\" | \"left\" | \"right\";\n\n  return (\n    <Section\n      style={{ backgroundColor: resolved.pageBackgroundColor }}\n      width=\"100%\"\n    >\n      <Fragment>\n        <Row>\n          <Column>&zwj;</Column>\n          <Column\n            style={{\n              backgroundColor: resolved.backgroundColor,\n              maxWidth: \"100%\",\n              width: \"600px\",\n            }}\n          >\n            <Section width=\"100%\">\n              <Fragment>\n                <Row>\n                  <Column style={{ padding: \"44px 24px 24px\", textAlign }}>\n                    <Text\n                      style={{\n                        color: resolved.headingColor,\n                        fontFamily,\n                        fontSize: \"20px\",\n                        fontWeight: 600,\n                        lineHeight: \"28px\",\n                        margin: 0,\n                      }}\n                    >\n                      <Multiline text={resolved.heading} />\n                    </Text>\n                    <Section style={{ lineHeight: \"28px\" }}>&zwj;</Section>\n                    <Text\n                      style={{\n                        color: resolved.textColor,\n                        fontFamily,\n                        fontSize: \"16px\",\n                        lineHeight: \"24px\",\n                        margin: 0,\n                      }}\n                    >\n                      {resolved.subtext}\n                    </Text>\n                    <Section style={{ lineHeight: \"28px\" }}>&zwj;</Section>\n                    <Section>\n                      <Link\n                        href={resolved.ctaHref}\n                        style={{\n                          backgroundColor: resolved.buttonColor,\n                          borderRadius: \"8px\",\n                          color: resolved.buttonTextColor,\n                          display: \"inline-block\",\n                          fontFamily,\n                          fontSize: \"16px\",\n                          fontWeight: 500,\n                          lineHeight: 1,\n                          padding: \"14px 48px\",\n                          textDecoration: \"none\",\n                        }}\n                      >\n                        <span\n                          style={{ marginRight: \"8px\", msoTextRaise: \"14px\" }}\n                        >\n                          {resolved.ctaLabel}\n                        </span>\n                        <span style={{ msoTextRaise: \"14px\" }}>\n                          <Img\n                            alt=\"\"\n                            src=\"https://emailcn.vercel.app/api/email-assets/icon-arrow-right.png\"\n                            style={{\n                              maxWidth: \"100%\",\n                              verticalAlign: \"baseline\",\n                            }}\n                            width={12}\n                          />\n                        </span>\n                      </Link>\n                    </Section>\n                    <Section style={{ lineHeight: \"96px\" }}>&zwj;</Section>\n                    <Img\n                      alt={resolved.logoAlt}\n                      src={resolved.logoSrc}\n                      style={{ maxWidth: \"100%\", verticalAlign: \"middle\" }}\n                      width={55}\n                    />\n                    <Section style={{ lineHeight: \"36px\" }}>&zwj;</Section>\n                    <Text\n                      style={{\n                        color: resolved.mutedTextColor,\n                        fontFamily,\n                        fontSize: \"16px\",\n                        lineHeight: \"24px\",\n                        margin: 0,\n                      }}\n                    >\n                      © 2026 emailcn. All rights reserved.\n                      <br />\n                      <br />\n                      Want to change how you receive these emails?\n                      <br />\n                      You can{\" \"}\n                      <Link\n                        href={resolved.updatePreferencesHref}\n                        style={{\n                          color: resolved.mutedTextColor,\n                          textDecoration: \"underline\",\n                        }}\n                      >\n                        update your preferences\n                      </Link>{\" \"}\n                      or{\" \"}\n                      <Link\n                        href={resolved.unsubscribeHref}\n                        style={{\n                          color: resolved.mutedTextColor,\n                          textDecoration: \"underline\",\n                        }}\n                      >\n                        unsubscribe from this list.\n                      </Link>\n                    </Text>\n                  </Column>\n                </Row>\n              </Fragment>\n            </Section>\n          </Column>\n          <Column>&zwj;</Column>\n        </Row>\n      </Fragment>\n    </Section>\n  );\n};\n\nexport const FooterWithContentAndCta = ({\n  pageBackgroundColor = \"#f1f5f9\",\n  theme: _theme = defaultTheme,\n  variant = \"centered\",\n  ...props\n}: FooterWithContentAndCtaProps) => (\n  <Html>\n    <Head>\n      <DefaultFonts />\n    </Head>\n    <Preview>{props.heading ?? defaults.heading.replaceAll(\"\\n\", \" \")}</Preview>\n    <Body\n      style={{ backgroundColor: pageBackgroundColor, fontFamily, margin: 0 }}\n    >\n      <FooterWithContentAndCtaSection\n        {...props}\n        pageBackgroundColor={pageBackgroundColor}\n        variant={variant}\n      />\n    </Body>\n  </Html>\n);\n\nFooterWithContentAndCta.PreviewProps = {\n  theme: defaultTheme,\n  variant: \"centered\",\n} satisfies FooterWithContentAndCtaProps;\n",
      "type": "registry:component",
      "target": "components/email/footer-with-content-and-cta.tsx"
    }
  ],
  "categories": [
    "email-component"
  ],
  "type": "registry:component"
}
