{
  "$schema": "https://ui.shadcn.com/schema/registry-item.json",
  "name": "logo-cloud-with-borders",
  "title": "Logo Cloud With Borders",
  "description": "Marketing logos variant for email templates",
  "dependencies": [
    "jsx-email"
  ],
  "registryDependencies": [
    "https://emailcn.vercel.app/r/jsx-email/default-fonts.json",
    "https://emailcn.vercel.app/r/jsx-email/theme-default.json"
  ],
  "files": [
    {
      "path": "registry/bases/jsx-email/ui/marketing/logos/logo-cloud-with-borders.tsx",
      "content": "import {\n  Body,\n  Head,\n  Html,\n  Preview,\n  Column,\n  Section,\n  Row,\n  Heading,\n  Text,\n  Img,\n} from \"jsx-email\";\nimport { Fragment } from \"react\";\n\nimport { DefaultFonts } from \"@/components/email/default\";\nimport { defaultTheme } from \"@/components/email/theme-default\";\nimport type { EmailThemeTokens } from \"@/components/email/theme-default\";\n\nexport type LogoCloudWithBordersVariant =\n  | \"minimal\"\n  | \"with-title\"\n  | \"with-description\"\n  | \"full\"\n  | \"flush\";\n\nexport interface LogoCloudWithBordersProps {\n  theme?: EmailThemeTokens;\n  title?: string;\n  description?: string;\n  logos?: { alt: string; src: string; width: number }[];\n  pageBackgroundColor?: string;\n  backgroundColor?: string;\n  borderColor?: string;\n  titleColor?: string;\n  textColor?: string;\n  variant?: LogoCloudWithBordersVariant;\n}\n\nconst fontFamily =\n  'Inter, ui-sans-serif, system-ui, -apple-system, \"Segoe UI\", sans-serif';\n\nconst responsiveStyles = `\n  @media only screen and (max-width: 599px) {\n    .border-logo-flush-table { margin: 0 auto !important; }\n    .border-logo-flush-item { display: block !important; width: 100% !important; }\n    .border-logo-flush-divider {\n      display: block !important;\n      line-height: 1px !important;\n      width: 100% !important;\n    }\n    .border-logo-flush-bottom { display: none !important; }\n    .border-logo-description-gap { line-height: 20px !important; }\n  }\n  @media only screen and (max-width: 430px) {\n    .border-logo-item { display: block !important; width: 100% !important; }\n    .border-logo-divider {\n      display: block !important;\n      line-height: 1px !important;\n      width: 100% !important;\n    }\n  }\n`;\n\nconst defaultLogos = [\n  {\n    alt: \"Stripe\",\n    src: \"https://emailcn.vercel.app/api/email-assets/logos/logo-stripe.png\",\n    width: 57,\n  },\n  {\n    alt: \"Apple Pay\",\n    src: \"https://emailcn.vercel.app/api/email-assets/logos/logo-apple-pay.png\",\n    width: 60,\n  },\n  {\n    alt: \"Mastercard\",\n    src: \"https://emailcn.vercel.app/api/email-assets/logos/logo-mastercard.png\",\n    width: 40,\n  },\n  {\n    alt: \"Visa\",\n    src: \"https://emailcn.vercel.app/api/email-assets/logos/logo-visa.png\",\n    width: 50,\n  },\n  {\n    alt: \"Klarna\",\n    src: \"https://emailcn.vercel.app/api/email-assets/logos/logo-klarna.png\",\n    width: 70,\n  },\n];\n\nconst defaults = {\n  backgroundColor: \"#fffffe\",\n  borderColor: \"#d1d5db\",\n  description:\n    \"We created a personal account for you. Please confirm your e-mail address and use our service to the maximum\",\n  logos: defaultLogos,\n  pageBackgroundColor: \"#f1f5f9\",\n  textColor: \"#4b5563\",\n  title: \"Supported payment services\",\n  titleColor: \"#030712\",\n};\n\ntype SectionProps = Omit<LogoCloudWithBordersProps, \"theme\">;\ntype ResolvedProps = typeof defaults & SectionProps;\ntype Logo = (typeof defaultLogos)[number];\n\nconst LogoItem = ({\n  className,\n  logo,\n  width,\n}: {\n  className: string;\n  logo: Logo;\n  width: string;\n}) => (\n  <Column\n    className={className}\n    style={{ lineHeight: \"64px\", textAlign: \"center\", width }}\n  >\n    <Img\n      alt={logo.alt}\n      src={logo.src}\n      style={{ maxWidth: \"100%\", verticalAlign: \"middle\" }}\n      width={logo.width}\n    />\n  </Column>\n);\n\nconst Divider = ({\n  className,\n  color,\n}: {\n  className: string;\n  color: string;\n}) => (\n  <Column\n    className={className}\n    style={{ backgroundColor: color, width: \"1px\" }}\n  >\n    &zwj;\n  </Column>\n);\n\nconst LogoRow = ({\n  flush = false,\n  logos,\n  props,\n}: {\n  flush?: boolean;\n  logos: Logo[];\n  props: ResolvedProps;\n}) => (\n  <Section\n    align={flush ? undefined : \"center\"}\n    className={flush ? \"border-logo-flush-table\" : undefined}\n    style={flush ? { width: \"100%\" } : { margin: \"0 auto\" }}\n  >\n    <Fragment>\n      <Row>\n        {logos.map((logo, index) => (\n          <Fragment key={logo.alt + logo.src}>\n            {index > 0 ? (\n              <Divider\n                className={\n                  flush ? \"border-logo-flush-divider\" : \"border-logo-divider\"\n                }\n                color={props.borderColor}\n              />\n            ) : null}\n            <LogoItem\n              className={flush ? \"border-logo-flush-item\" : \"border-logo-item\"}\n              logo={logo}\n              width={\n                flush && (index === 0 || index === logos.length - 1)\n                  ? \"132px\"\n                  : \"112px\"\n              }\n            />\n          </Fragment>\n        ))}\n      </Row>\n      {flush ? (\n        <Row>\n          <Column\n            className=\"border-logo-flush-bottom\"\n            colSpan={9}\n            style={{\n              backgroundColor: props.borderColor,\n              lineHeight: \"1px\",\n            }}\n          >\n            &zwj;\n          </Column>\n        </Row>\n      ) : null}\n    </Fragment>\n  </Section>\n);\n\nconst Title = ({ props }: { props: ResolvedProps }) => (\n  <Heading\n    style={{\n      color: props.titleColor,\n      fontFamily,\n      fontSize: \"20px\",\n      fontWeight: 600,\n      lineHeight: \"28px\",\n      margin: 0,\n      textAlign: \"center\",\n    }}\n    as=\"h3\"\n  >\n    {props.title}\n  </Heading>\n);\n\nconst Description = ({ props }: { props: ResolvedProps }) => (\n  <Text\n    style={{\n      color: props.textColor,\n      fontFamily,\n      fontSize: \"16px\",\n      fontWeight: 300,\n      lineHeight: \"24px\",\n      margin: 0,\n      textAlign: \"center\",\n    }}\n  >\n    {props.description}\n  </Text>\n);\n\nexport const LogoCloudWithBordersSection = (props: SectionProps) => {\n  const variant = props.variant ?? \"full\";\n  const resolved = { ...defaults, ...props } as ResolvedProps;\n  const logos = resolved.logos.slice(0, 5) as Logo[];\n  const flush = variant === \"flush\";\n  const showTitle = variant === \"with-title\" || variant === \"full\" || flush;\n  const showDescription =\n    variant === \"with-description\" || variant === \"full\" || flush;\n\n  const rows = flush ? (\n    <LogoRow flush logos={logos} props={resolved} />\n  ) : (\n    <>\n      <Section align=\"center\" style={{ margin: \"0 auto\" }}>\n        <Fragment>\n          <Row>\n            {logos.slice(0, 3).map((logo, index) => (\n              <Fragment key={logo.alt + logo.src}>\n                {index > 0 ? (\n                  <Divider\n                    className=\"border-logo-divider\"\n                    color={resolved.borderColor}\n                  />\n                ) : null}\n                <LogoItem\n                  className=\"border-logo-item\"\n                  logo={logo}\n                  width=\"112px\"\n                />\n              </Fragment>\n            ))}\n          </Row>\n          <Row>\n            <Column\n              className=\"border-logo-divider\"\n              colSpan={5}\n              style={{\n                backgroundColor: resolved.borderColor,\n                lineHeight: \"1px\",\n              }}\n            >\n              &zwj;\n            </Column>\n          </Row>\n        </Fragment>\n      </Section>\n      <LogoRow logos={logos.slice(3, 5)} props={resolved} />\n    </>\n  );\n\n  return (\n    <Section\n      style={{ backgroundColor: resolved.pageBackgroundColor }}\n      width=\"100%\"\n    >\n      <Fragment>\n        <Row>\n          <Column>&zwj;</Column>\n          <Column\n            style={{\n              backgroundColor: resolved.backgroundColor,\n              maxWidth: \"100%\",\n              paddingBottom: \"44px\",\n              width: \"600px\",\n            }}\n          >\n            {flush ? (\n              <Section width=\"100%\">\n                <Fragment>\n                  <Row>\n                    <Column style={{ padding: \"0 24px\" }}>\n                      <Section style={{ lineHeight: \"44px\" }}>&zwj;</Section>\n                      {showTitle ? <Title props={resolved} /> : null}\n                    </Column>\n                  </Row>\n                  <Row>\n                    <Column>\n                      <Section style={{ lineHeight: \"44px\" }}>&zwj;</Section>\n                      {rows}\n                    </Column>\n                  </Row>\n                  {showDescription ? (\n                    <Row>\n                      <Column style={{ padding: \"0 24px\" }}>\n                        <Section\n                          className=\"border-logo-description-gap\"\n                          style={{ lineHeight: \"36px\" }}\n                        >\n                          &zwj;\n                        </Section>\n                        <Description props={resolved} />\n                      </Column>\n                    </Row>\n                  ) : null}\n                </Fragment>\n              </Section>\n            ) : (\n              <Section width=\"100%\">\n                <Fragment>\n                  <Row>\n                    <Column style={{ padding: \"0 24px\", textAlign: \"center\" }}>\n                      <Section style={{ lineHeight: \"44px\" }}>&zwj;</Section>\n                      {showTitle ? (\n                        <>\n                          <Title props={resolved} />\n                          <Section style={{ lineHeight: \"44px\" }}>\n                            &zwj;\n                          </Section>\n                        </>\n                      ) : null}\n                      {rows}\n                      {showDescription ? (\n                        <>\n                          <Section\n                            className=\"border-logo-description-gap\"\n                            style={{ lineHeight: \"36px\" }}\n                          >\n                            &zwj;\n                          </Section>\n                          <Description props={resolved} />\n                        </>\n                      ) : null}\n                    </Column>\n                  </Row>\n                </Fragment>\n              </Section>\n            )}\n          </Column>\n          <Column>&zwj;</Column>\n        </Row>\n      </Fragment>\n    </Section>\n  );\n};\n\nexport const LogoCloudWithBorders = ({\n  pageBackgroundColor = \"#f1f5f9\",\n  theme: _theme = defaultTheme,\n  variant = \"full\",\n  ...props\n}: LogoCloudWithBordersProps) => (\n  <Html>\n    <Head>\n      <DefaultFonts />\n      <style dangerouslySetInnerHTML={{ __html: responsiveStyles }} />\n    </Head>\n    <Preview>Supported payment services</Preview>\n    <Body\n      style={{ backgroundColor: pageBackgroundColor, fontFamily, margin: 0 }}\n    >\n      <LogoCloudWithBordersSection\n        {...props}\n        pageBackgroundColor={pageBackgroundColor}\n        variant={variant}\n      />\n    </Body>\n  </Html>\n);\n\nLogoCloudWithBorders.PreviewProps = {\n  theme: defaultTheme,\n  variant: \"full\",\n} satisfies LogoCloudWithBordersProps;\n",
      "type": "registry:component",
      "target": "components/email/logo-cloud-with-borders.tsx"
    }
  ],
  "categories": [
    "email-component"
  ],
  "type": "registry:component"
}
