{
  "$schema": "https://ui.shadcn.com/schema/registry-item.json",
  "name": "two-thirds-bento-grid-with-stats",
  "title": "Two Thirds Bento Grid With Stats",
  "description": "Marketing bento-grids variant for email templates",
  "dependencies": [
    "jsx-email"
  ],
  "registryDependencies": [
    "https://emailcn.dev/r/jsx-email/theme-default.json"
  ],
  "files": [
    {
      "path": "registry/bases/jsx-email/ui/marketing/bento-grids/two-thirds-bento-grid-with-stats.tsx",
      "content": "/* eslint-disable no-nested-ternary, no-unused-vars, complexity, no-negated-condition, no-empty-pattern */\nimport {\n  Body,\n  Column,\n  Container,\n  Head,\n  Html,\n  Img,\n  Preview,\n  Row,\n  Section,\n  Text,\n} from \"jsx-email\";\n\nimport { defaultTheme } from \"@/components/emails/themes/theme-default\";\nimport type { EmailThemeTokens } from \"@/components/emails/themes/theme-default\";\n\nexport type BentoGridProductVariant =\n  | \"default\"\n  | \"slanted-left\"\n  | \"slanted-right\";\nexport interface BentoGridProductProps {\n  theme?: EmailThemeTokens;\n  heading?: string;\n  products?: {\n    imageUrl: string;\n    imageAlt: string;\n    name: string;\n    price: string;\n  }[];\n  variant?: BentoGridProductVariant;\n}\nconst BentoGridProductSection = ({\n  heading,\n  products,\n  theme,\n  variant,\n}: {\n  heading: string;\n  products: BentoGridProductProps[\"products\"];\n  theme: EmailThemeTokens;\n  variant: BentoGridProductVariant;\n}) => (\n  <Section\n    style={{\n      backgroundColor: theme.colorBackground,\n      padding: `${theme.spacingXl ?? \"48px\"} 0`,\n    }}\n  >\n    <Row>\n      {heading ? (\n        <Column>\n          <Text\n            style={{\n              color: theme.colorText,\n              fontFamily: theme.fontFamily,\n              fontSize: theme.fontSizeHeading,\n              fontWeight: theme.fontWeightBold,\n              margin: 0,\n              paddingBottom: theme.spacingXl ?? \"48px\",\n              textAlign: \"center\",\n            }}\n          >\n            {heading}\n          </Text>\n        </Column>\n      ) : null}\n      {(products ?? []).slice(0, 3).map((p, i) => (\n        <Column\n          key={p.name + i}\n          style={{ padding: \"8px\", verticalAlign: \"top\", width: \"33.33%\" }}\n        >\n          <Img\n            alt={p.imageAlt}\n            src={p.imageUrl}\n            width={190}\n            style={{\n              borderRadius: theme.borderRadius,\n              display: \"block\",\n              margin: \"0 auto\",\n              maxWidth: \"100%\",\n              paddingBottom: theme.spacingBase ?? \"12px\",\n            }}\n          />\n          <Text\n            style={{\n              color: theme.colorText,\n              fontFamily: theme.fontFamily,\n              fontSize: theme.fontSizeBase,\n              fontWeight: theme.fontWeightMedium,\n              margin: 0,\n              paddingBottom: theme.spacingBase ?? \"4px\",\n              textAlign: \"center\",\n            }}\n          >\n            {p.name}\n          </Text>\n          <Text\n            style={{\n              color: theme.colorPrimary,\n              fontFamily: theme.fontFamily,\n              fontSize: theme.fontSizeSm,\n              fontWeight: theme.fontWeightMedium,\n              margin: 0,\n              textAlign: \"center\",\n            }}\n          >\n            {p.price}\n          </Text>\n        </Column>\n      ))}\n    </Row>\n  </Section>\n);\nexport const TwoThirdsBentoGridWithStats = ({\n  theme = defaultTheme,\n  heading = \"Products\",\n  products = [\n    {\n      imageAlt: \"Product 1\",\n      imageUrl: \"https://static.photos/technology/300x300/2\",\n      name: \"Product One\",\n      price: \"$29\",\n    },\n    {\n      imageAlt: \"Product 2\",\n      imageUrl: \"https://static.photos/technology/300x300/3\",\n      name: \"Product Two\",\n      price: \"$49\",\n    },\n    {\n      imageAlt: \"Product 3\",\n      imageUrl: \"https://static.photos/technology/300x300/4\",\n      name: \"Product Three\",\n      price: \"$79\",\n    },\n  ],\n  variant = \"default\",\n}: BentoGridProductProps) => (\n  <Html>\n    <Head />\n    <Preview>bento product</Preview>\n    <Body\n      style={{\n        backgroundColor: theme.colorBackground,\n        color: theme.colorTextMuted,\n        fontFamily: theme.fontFamily,\n        fontSize: theme.fontSizeBase,\n        lineHeight: theme.lineHeightBase,\n        margin: 0,\n      }}\n    >\n      <Container style={{ maxWidth: theme.containerWidth }}>\n        <Section style={{ padding: \"0\" }}>\n          <BentoGridProductSection\n            heading={heading}\n            products={products}\n            theme={theme}\n            variant={variant}\n          />\n        </Section>\n      </Container>\n    </Body>\n  </Html>\n);\nTwoThirdsBentoGridWithStats.PreviewProps = {\n  heading: \"Featured Products\",\n  products: [\n    {\n      imageAlt: \"Widget\",\n      imageUrl: \"https://static.photos/technology/300x300/5\",\n      name: \"Premium Widget\",\n      price: \"$39\",\n    },\n    {\n      imageAlt: \"Gadget\",\n      imageUrl: \"https://static.photos/technology/300x300/6\",\n      name: \"Super Gadget\",\n      price: \"$59\",\n    },\n    {\n      imageAlt: \"Tool\",\n      imageUrl: \"https://static.photos/technology/300x300/7\",\n      name: \"Pro Tool\",\n      price: \"$99\",\n    },\n  ],\n  theme: defaultTheme,\n  variant: \"default\",\n} satisfies BentoGridProductProps;\n",
      "type": "registry:component",
      "target": "components/emails/marketing/bento-grids/two-thirds-bento-grid-with-stats.tsx"
    }
  ],
  "categories": [
    "email-component"
  ],
  "type": "registry:component"
}
