{
  "$schema": "https://ui.shadcn.com/schema/registry-item.json",
  "name": "hero-with-image-grid",
  "title": "Hero With Image Grid",
  "description": "Marketing hero variant for email templates",
  "dependencies": [
    "react-email"
  ],
  "registryDependencies": [
    "https://emailcn.vercel.app/r/react-email/default-fonts.json",
    "https://emailcn.vercel.app/r/react-email/theme-default.json"
  ],
  "files": [
    {
      "path": "registry/bases/react-email/ui/marketing/hero/hero-with-image-grid.tsx",
      "content": "import {\n  Body,\n  Button,\n  Container,\n  Head,\n  Html,\n  Img,\n  Preview,\n  Section,\n  Tailwind,\n  Text,\n  Heading,\n  Link,\n} from \"react-email\";\nimport type { TailwindConfig } from \"react-email\";\n\nimport { DefaultFonts } from \"@/components/email/default\";\nimport { defaultTheme } from \"@/components/email/theme-default\";\n\nexport type HeroWithImageGridVariant =\n  | \"images-bottom\"\n  | \"images-top\"\n  | \"offset-images-bottom\"\n  | \"offset-images-top\";\n\nexport interface HeroWithImageGridImage {\n  alt: string;\n  src: string;\n}\n\nexport interface HeroWithImageGridProps {\n  theme?: TailwindConfig;\n  eyebrow?: string;\n  heading?: string;\n  subheading?: string;\n  description?: string;\n  ctaLabel?: string;\n  ctaHref?: string;\n  images?: HeroWithImageGridImage[];\n  logoSrc?: string;\n  logoAlt?: string;\n  logoHref?: string;\n  pageBackgroundColor?: string;\n  backgroundColor?: string;\n  buttonBackgroundColor?: string;\n  buttonTextColor?: string;\n  variant?: HeroWithImageGridVariant;\n}\n\nconst fontFamily =\n  'Inter, ui-sans-serif, system-ui, -apple-system, \"Segoe UI\", sans-serif';\n\nconst responsiveStyles = `\n  @media only screen and (max-width: 599px) {\n    .hero-image-grid-container {\n      width: 100% !important;\n    }\n\n    .hero-image-grid-heading {\n      font-size: 36px !important;\n      line-height: 40px !important;\n    }\n\n    .hero-image-grid-image {\n      margin: 0 12px 24px !important;\n      max-width: 96px !important;\n    }\n\n    .hero-image-grid-gap {\n      display: none !important;\n    }\n  }\n`;\n\nconst regularImages: HeroWithImageGridImage[] = Array.from(\n  { length: 7 },\n  (_, index) => ({\n    alt: `Image ${index + 1}`,\n    src: `https://emailcn.vercel.app/api/email-assets/hero/mosaic-${index + 1}.jpg`,\n  })\n);\n\nconst offsetImageNumbers = [1, 2, 7, 10, 4, 6, 8, 9, 5, 11];\n\nconst offsetImages: HeroWithImageGridImage[] = offsetImageNumbers.map(\n  (imageNumber, index) => ({\n    alt: `Image ${index + 1}`,\n    src: `https://emailcn.vercel.app/api/email-assets/hero/mosaic-${imageNumber}.jpg`,\n  })\n);\n\nconst Spacer = ({ height }: { height: number }) => (\n  <Section style={{ fontSize: 0, height, lineHeight: `${height}px` }}>\n    &zwj;\n  </Section>\n);\n\nconst ImageGallery = ({\n  images,\n  offset,\n}: {\n  images: HeroWithImageGridImage[];\n  offset: boolean;\n}) => {\n  const defaults = offset ? offsetImages : regularImages;\n  const resolvedImages = defaults.map((fallback, index) =>\n    images[index] ? { ...fallback, ...images[index] } : fallback\n  );\n  const imageWidth = offset ? 91 : 120;\n  const wrapAfter = offset ? 4 : 3;\n\n  return (\n    <Section style={{ fontSize: 0, textAlign: \"center\" }}>\n      {resolvedImages.map((image, index) => (\n        <span key={`${image.src}-${index}`}>\n          <Img\n            alt={image.alt}\n            className=\"hero-image-grid-image\"\n            src={image.src}\n            width={imageWidth}\n            style={{\n              borderRadius: \"4px\",\n              display: \"inline-block\",\n              marginBottom: \"48px\",\n              marginTop: offset && index % 2 === 0 ? \"24px\" : 0,\n              maxWidth: \"100%\",\n              verticalAlign: \"middle\",\n            }}\n          />\n          {index < resolvedImages.length - 1 && index !== wrapAfter ? (\n            <span\n              className=\"hero-image-grid-gap\"\n              style={{ display: \"inline-block\", width: \"24px\" }}\n            >\n              &nbsp;\n            </span>\n          ) : null}\n        </span>\n      ))}\n    </Section>\n  );\n};\n\ntype SectionProps = Required<\n  Omit<HeroWithImageGridProps, \"theme\" | \"variant\">\n> & {\n  variant: HeroWithImageGridVariant;\n};\n\nexport const HeroWithImageGridSection = ({\n  backgroundColor,\n  buttonBackgroundColor,\n  buttonTextColor,\n  ctaHref,\n  ctaLabel,\n  description,\n  eyebrow,\n  heading,\n  images,\n  logoAlt,\n  logoHref,\n  logoSrc,\n  subheading,\n  variant,\n}: SectionProps) => {\n  const imagesFirst = variant.endsWith(\"-top\");\n  const offset = variant.startsWith(\"offset-\");\n  const gallery = <ImageGallery images={images} offset={offset} />;\n  const content = (\n    <Section style={{ padding: \"0 24px\", textAlign: \"center\" }}>\n      <Spacer height={imagesFirst ? 20 : 44} />\n      <Text\n        style={{\n          color: \"#030712\",\n          fontFamily,\n          fontSize: \"16px\",\n          fontWeight: 200,\n          lineHeight: \"24px\",\n          margin: 0,\n        }}\n      >\n        {eyebrow}\n      </Text>\n      <Heading\n        className=\"hero-image-grid-heading\"\n        style={{\n          color: \"#030712\",\n          fontFamily,\n          fontSize: \"48px\",\n          fontWeight: 500,\n          lineHeight: \"58px\",\n          margin: 0,\n        }}\n        as=\"h1\"\n      >\n        {heading}\n      </Heading>\n      <Text\n        style={{\n          color: \"#030712\",\n          fontFamily,\n          fontSize: \"18px\",\n          lineHeight: \"28px\",\n          margin: 0,\n        }}\n      >\n        {subheading}\n      </Text>\n      <Text\n        style={{\n          color: \"#4b5563\",\n          fontFamily,\n          fontSize: \"16px\",\n          fontWeight: 300,\n          lineHeight: \"24px\",\n          margin: \"44px 0 0\",\n        }}\n      >\n        {description}\n      </Text>\n    </Section>\n  );\n\n  return (\n    <Section style={{ backgroundColor, padding: \"44px 0\" }}>\n      <Section style={{ textAlign: \"center\" }}>\n        <Link href={logoHref}>\n          <Img\n            alt={logoAlt}\n            src={logoSrc}\n            width=\"165\"\n            style={{ display: \"inline-block\", maxWidth: \"100%\" }}\n          />\n        </Link>\n      </Section>\n      {imagesFirst ? (\n        <>\n          <Spacer height={44} />\n          {gallery}\n          {content}\n        </>\n      ) : (\n        <>\n          {content}\n          <Spacer height={44} />\n          {gallery}\n        </>\n      )}\n      <Spacer height={44} />\n      <Section style={{ textAlign: \"center\" }}>\n        {ctaLabel && ctaHref ? (\n          <Button\n            href={ctaHref}\n            style={{\n              backgroundColor: buttonBackgroundColor,\n              borderRadius: \"8px\",\n              color: buttonTextColor,\n              display: \"inline-block\",\n              fontFamily,\n              fontSize: \"16px\",\n              fontWeight: 500,\n              lineHeight: 1,\n              padding: \"14px 20px\",\n              textDecoration: \"none\",\n            }}\n          >\n            <span style={{ marginRight: \"8px\" }}>{ctaLabel}</span>\n            <Img\n              alt=\"\"\n              src=\"https://emailcn.vercel.app/api/email-assets/icon-arrow-right.png\"\n              width=\"12\"\n              style={{\n                display: \"inline-block\",\n                maxWidth: \"100%\",\n                verticalAlign: \"baseline\",\n              }}\n            />\n          </Button>\n        ) : null}\n      </Section>\n    </Section>\n  );\n};\n\nexport const HeroWithImageGrid = ({\n  backgroundColor = \"#fffffe\",\n  buttonBackgroundColor = \"#4f46e5\",\n  buttonTextColor = \"#fffffe\",\n  ctaHref = \"https://example.com\",\n  ctaLabel = \"Discover now\",\n  description = \"A curated look at design, culture, and creativity in motion. From classics reborn to boundary-pushing silhouettes — see what's shaping the streets today.\",\n  eyebrow = \"NEW ARRIVALS\",\n  heading = \"Step into the hype\",\n  images = [],\n  logoAlt = \"emailcn\",\n  logoHref = \"https://example.com\",\n  logoSrc = \"https://emailcn.vercel.app/api/email-assets/emailcn-logo.png\",\n  pageBackgroundColor = \"#f1f5f9\",\n  subheading = \"The evolution of the sneaker\",\n  theme = defaultTheme,\n  variant = \"images-bottom\",\n}: HeroWithImageGridProps) => (\n  <Html>\n    <Head>\n      <DefaultFonts />\n      <style dangerouslySetInnerHTML={{ __html: responsiveStyles }} />\n    </Head>\n    <Preview>{`${heading} — ${subheading}`}</Preview>\n    <Tailwind config={theme}>\n      <Body\n        style={{ backgroundColor: pageBackgroundColor, fontFamily, margin: 0 }}\n      >\n        <Container\n          className=\"hero-image-grid-container\"\n          style={{\n            backgroundColor,\n            margin: \"0 auto\",\n            maxWidth: \"600px\",\n            width: \"600px\",\n          }}\n        >\n          <HeroWithImageGridSection\n            backgroundColor={backgroundColor}\n            buttonBackgroundColor={buttonBackgroundColor}\n            buttonTextColor={buttonTextColor}\n            ctaHref={ctaHref}\n            ctaLabel={ctaLabel}\n            description={description}\n            eyebrow={eyebrow}\n            heading={heading}\n            images={images}\n            logoAlt={logoAlt}\n            logoHref={logoHref}\n            logoSrc={logoSrc}\n            pageBackgroundColor={pageBackgroundColor}\n            subheading={subheading}\n            variant={variant}\n          />\n        </Container>\n      </Body>\n    </Tailwind>\n  </Html>\n);\n\nHeroWithImageGrid.PreviewProps = {\n  backgroundColor: \"#fffffe\",\n  buttonBackgroundColor: \"#4f46e5\",\n  buttonTextColor: \"#fffffe\",\n  ctaHref: \"https://example.com\",\n  ctaLabel: \"Discover now\",\n  description:\n    \"A curated look at design, culture, and creativity in motion. From classics reborn to boundary-pushing silhouettes — see what's shaping the streets today.\",\n  eyebrow: \"NEW ARRIVALS\",\n  heading: \"Step into the hype\",\n  images: [],\n  logoAlt: \"emailcn\",\n  logoHref: \"https://example.com\",\n  logoSrc: \"https://emailcn.vercel.app/api/email-assets/emailcn-logo.png\",\n  pageBackgroundColor: \"#f1f5f9\",\n  subheading: \"The evolution of the sneaker\",\n  theme: defaultTheme,\n  variant: \"images-bottom\",\n} satisfies HeroWithImageGridProps;\n",
      "type": "registry:component",
      "target": "components/email/hero-with-image-grid.tsx"
    }
  ],
  "categories": [
    "email-component"
  ],
  "type": "registry:component"
}
