{
  "$schema": "https://ui.shadcn.com/schema/registry-item.json",
  "name": "mjml-email-content-grid",
  "title": "Email Content Grid (MJML)",
  "description": "Grid layout for showcasing features or content in email templates",
  "dependencies": [
    "@faire/mjml-react",
    "mjml-browser"
  ],
  "registryDependencies": [
    "https://emailcn.com/r/email-theme-default.json"
  ],
  "files": [
    {
      "path": "registry/bases/mjml-react/ui/content-grid.tsx",
      "content": "import {\n  MjmlColumn,\n  MjmlImage,\n  MjmlSection,\n  MjmlText,\n} from \"@faire/mjml-react\";\n\nimport { resolveEmailTheme } from \"@/registry/lib/resolve-theme\";\nimport type { EmailTheme } from \"@/registry/themes/default\";\nimport { theme as defaultTheme } from \"@/registry/themes/default\";\n\nexport interface ContentGridProps {\n  theme?: EmailTheme;\n  columnCount?: 2 | 3;\n  columns?: {\n    iconUrl?: string;\n    title: string;\n    description: string;\n  }[];\n}\n\nexport const ContentGrid = ({\n  theme = defaultTheme,\n  columnCount = 2,\n  columns = [\n    { description: \"Description for feature 1\", title: \"Feature 1\" },\n    { description: \"Description for feature 2\", title: \"Feature 2\" },\n  ],\n}: ContentGridProps) => {\n  const t = resolveEmailTheme(theme);\n  const slice = columns.slice(0, columnCount);\n  const widthPct =\n    columnCount === 3 ? `${100 / 3}%` : (columnCount === 2 ? \"50%\" : \"100%\");\n\n  return (\n    <MjmlSection padding={`${t.spacing.xl ?? \"24px\"} 0`}>\n      {slice.map((col, index) => (\n        <MjmlColumn key={col.title} width={widthPct} padding={t.spacing.md}>\n          {col.iconUrl ? (\n            <MjmlImage\n              alt={col.title}\n              borderRadius={t.borderRadius.md}\n              height={48}\n              paddingBottom={t.spacing.md}\n              src={col.iconUrl}\n              width={48}\n            />\n          ) : null}\n          <MjmlText\n            color={t.colors.foreground}\n            fontFamily={t.fontFamily.sans}\n            fontSize={t.fontSize.lg ?? \"16px\"}\n            fontWeight={t.fontWeight.medium ?? \"500\"}\n            paddingBottom={t.spacing.sm}\n          >\n            {col.title}\n          </MjmlText>\n          <MjmlText\n            color={t.colors[\"foreground-muted\"]}\n            fontFamily={t.fontFamily.sans}\n            fontSize={t.fontSize.base ?? \"14px\"}\n            lineHeight={t.lineHeight.snug}\n          >\n            {col.description}\n          </MjmlText>\n        </MjmlColumn>\n      ))}\n    </MjmlSection>\n  );\n};\n\nContentGrid.PreviewProps = {\n  columnCount: 2,\n  columns: [\n    {\n      description: \"Lightning-fast load times for your emails.\",\n      iconUrl: \"https://example.com/icon1.png\",\n      title: \"Fast Performance\",\n    },\n    {\n      description: \"Simple API to get started in minutes.\",\n      iconUrl: \"https://example.com/icon2.png\",\n      title: \"Easy Integration\",\n    },\n  ],\n  theme: defaultTheme,\n} satisfies ContentGridProps;\n\nexport default ContentGrid;\n",
      "type": "registry:component"
    }
  ],
  "categories": [
    "email-component"
  ],
  "type": "registry:component"
}